LICENSE
MANIFEST.in
README.rst
setup.py
data/masterTable.xml
data/owndc-routes.xml
owndc/__init__.py
owndc/application.wadl
owndc/owndc.py
owndc/owndccli.py
owndc/owndcupdate.py
owndc.egg-info/PKG-INFO
owndc.egg-info/SOURCES.txt
owndc.egg-info/dependency_links.txt
owndc.egg-info/entry_points.txt
owndc.egg-info/requires.txt
owndc.egg-info/top_level.txt
owndc/routing/__init__.py
owndc/routing/routing.py
owndc/routing/routeutils/__init__.py
owndc/routing/routeutils/routing.py
owndc/routing/routeutils/unittestTools.py
owndc/routing/routeutils/utils.py
owndc/routing/routeutils/wsgicomm.py
tests/test-masterTable.xml
tests/test-owndc-routes.xml
tests/test-owndc.cfg