Metadata-Version: 1.2
Name: owndc
Version: 0.9.1a1.dev37
Summary: owndc: An FDSN Virtual Datacentre for SeisComP3
Home-page: https://github.com/javiquinte/owndc
Author: Javier Quinteros
Author-email: javier@gfz-potsdam.de
License: GPLv3
Keywords: seismology waveforms federation fdsn-ws
Platform: UNKNOWN
Classifier: Development Status :: 3 - Alpha
Classifier: Environment :: No Input/Output (Daemon)
Classifier: Framework :: CherryPy
Classifier: Intended Audience :: Science/Research
Classifier: License :: OSI Approved :: GNU General Public License v3 or later (GPLv3+)
Classifier: Natural Language :: English
Classifier: Operating System :: POSIX
Classifier: Operating System :: MacOS
Classifier: Programming Language :: Python :: 2
Classifier: Programming Language :: Python :: 2.7
Classifier: Topic :: Scientific/Engineering :: Interface Engine/Protocol Translator
Provides: owndc
Requires-Python: >=2.7, <3
